pyofo/__init__.py
pyofo/__version__.py
pyofo/auth.py
pyofo/config.py
pyofo/ofo.py
pyofo-0.1.2.dist-info/METADATA
pyofo-0.1.2.dist-info/RECORD
pyofo-0.1.2.dist-info/WHEEL
pyofo-0.1.2.dist-info/top_level.txt
